shared_models/__init__.py
shared_models/admin.py
shared_models/apps.py
shared_models/models.py
shared_models/tests.py
shared_models/views.py
shared_models/management/__init__.py
shared_models/management/commands/__init__.py
shared_models/management/commands/seed_default_data.py
shared_models/migrations/0001_initial.py
shared_models/migrations/0002_remove_changeorders_master_agreement_and_more.py
shared_models/migrations/0003_remove_changeorders_business_entity_and_more.py
shared_models/migrations/0004_remove_fileurls_file_type_and_more.py
shared_models/migrations/0005_remove_changeorderfiles_change_order_file_id_and_more.py
shared_models/migrations/0006_fileurls_reference_id_and_more.py
shared_models/migrations/0007_changeorders_files_changeorders_milestones.py
shared_models/migrations/0008_remove_changeorderresources_currency_id_and_more.py
shared_models/migrations/0009_alter_changeorderresourcerates_change_order_resource_and_more.py
shared_models/migrations/0010_alter_changeorderresourcerates_change_order_resource_and_more.py
shared_models/migrations/0011_otherratecardrates.py
shared_models/migrations/__init__.py
tangible_shared/__init__.py
tangible_shared/asgi.py
tangible_shared/settings.py
tangible_shared/urls.py
tangible_shared/wsgi.py
tangible_shared_models-1.0.1.dist-info/METADATA
tangible_shared_models-1.0.1.dist-info/WHEEL
tangible_shared_models-1.0.1.dist-info/top_level.txt
tangible_shared_models-1.0.1.dist-info/RECORD
